adafruit_mcp9808.py
adafruit_circuitpython_mcp9808-3.3.30.dist-info/licenses/LICENSE
adafruit_circuitpython_mcp9808-3.3.30.dist-info/METADATA
adafruit_circuitpython_mcp9808-3.3.30.dist-info/WHEEL
adafruit_circuitpython_mcp9808-3.3.30.dist-info/top_level.txt
adafruit_circuitpython_mcp9808-3.3.30.dist-info/RECORD
